collatz/__init__.py
collatz/__version__.py
collatz/parameterised.py
collatz-1.0.1.dist-info/LICENSE
collatz-1.0.1.dist-info/METADATA
collatz-1.0.1.dist-info/WHEEL
collatz-1.0.1.dist-info/top_level.txt
collatz-1.0.1.dist-info/RECORD
