Metadata-Version: 2.1
Name: collatz
Version: 1.0.1
Summary: Enabling experimenting with functions related to or involved in the Collatz conjecture.
Home-page: https://github.com/Skenvy/Collatz
Author: Skenvy
Author-email: nathan.a.z.levett@gmail.com
License: Apache Software License
Project-URL: Bug Tracker, https://github.com/Skenvy/Collatz/issues
Keywords: Collatz,Ulam,Kakutani's,Thwaites,Hasse's,Syracus
Classifier: Programming Language :: Python :: 3
Classifier: License :: OSI Approved :: Apache Software License
Classifier: Operating System :: OS Independent
Classifier: Topic :: Scientific/Engineering :: Mathematics
Requires-Python: >=3.6
License-File: LICENSE
